acn/__init__.py
acn/core.py
acn/engine.py
acn/exceptions.py
acn/key_manager.py
acn/primitives.py
acn/utils.py
acn/visualizer.py
acn_crypto-1.1.1.dist-info/METADATA
acn_crypto-1.1.1.dist-info/WHEEL
acn_crypto-1.1.1.dist-info/licenses/LICENSE
acn_crypto-1.1.1.dist-info/RECORD
