Metadata-Version: 2.4
Name: acn-crypto
Version: 1.1.1
Summary: An experimental, high-performance cryptographic library using a dynamic network architecture as the key.
Project-URL: Homepage, https://github.com/your_username/acn-project
Project-URL: Bug Tracker, https://github.com/your_username/acn-project/issues
Author-email: Mohammadmoein Pisoude <mmoeinp3@gmail.com>
License: MIT License
License-File: LICENSE
Classifier: Development Status :: 3 - Alpha
Classifier: Intended Audience :: Developers
Classifier: License :: OSI Approved :: MIT License
Classifier: Operating System :: OS Independent
Classifier: Programming Language :: Python :: 3
Classifier: Programming Language :: Python :: 3.8
Classifier: Programming Language :: Python :: 3.9
Classifier: Programming Language :: Python :: 3.10
Classifier: Programming Language :: Python :: 3.11
Classifier: Topic :: Security :: Cryptography
Classifier: Topic :: Software Development :: Libraries :: Python Modules
Requires-Python: >=3.8
Requires-Dist: cupy-cuda12x
Requires-Dist: graphviz
